README.rst
setup.py
version_probe/__init__.py
version_probe/app.py
version_probe/detect_version.py
version_probe.egg-info/PKG-INFO
version_probe.egg-info/SOURCES.txt
version_probe.egg-info/dependency_links.txt
version_probe.egg-info/entry_points.txt
version_probe.egg-info/requires.txt
version_probe.egg-info/top_level.txt