Metadata-Version: 1.1
Name: version-probe
Version: 0.1
Summary: Probe Python source code for language version.
Home-page: http://github.com/abingham/python-version-probe
Author: Austin Bingham
Author-email: austin@sixty-north.com
License: MIT License
Keywords: Python
Platform: UNKNOWN
Classifier: Development Status :: 3 - Alpha
Classifier: Programming Language :: Python
Classifier: License :: OSI Approved :: MIT License
Classifier: Operating System :: OS Independent
Classifier: Topic :: Software Development :: Libraries :: Python Modules
